qpic/Makefile
qpic/__init__.py
qpic/__main__.py
qpic/qpic.py
qpic-1.1.0.data/scripts/qpic
qpic-1.1.0.data/scripts/tikz2preview
qpic-1.1.0.dist-info/AUTHORS.rst
qpic-1.1.0.dist-info/LICENSE
qpic-1.1.0.dist-info/METADATA
qpic-1.1.0.dist-info/WHEEL
qpic-1.1.0.dist-info/top_level.txt
qpic-1.1.0.dist-info/RECORD
