Metadata-Version: 2.1
Name: qpic
Version: 1.1.0
Summary: Creating quantum circuit diagrams in TikZ
Home-page: https://github.com/qpic/qpic
Author: Sandy Kutin, Thomas Draper
Author-email: kutin@idaccr.org, tdraper@ccr-lajolla.org
License: GPL
Keywords: qpic
Classifier: Development Status :: 4 - Beta
Classifier: Intended Audience :: Developers
Classifier: License :: OSI Approved :: GNU General Public License v3 (GPLv3)
Classifier: Natural Language :: English
Classifier: Programming Language :: Python :: 2
Classifier: Programming Language :: Python :: 2.7
Classifier: Programming Language :: Python :: 3
Classifier: Programming Language :: Python :: 3.8
Classifier: Programming Language :: Python :: 3.9
Classifier: Programming Language :: Python :: 3.10
Classifier: Programming Language :: Python :: 3.11
License-File: LICENSE
License-File: AUTHORS.rst
